{
    "buffer_cpu_only": true,
    "num_envs": 1,
    "test_nepisode": 25,
    "test_interval": 1000,
    "log_interval": 1000,
    "runner_log_interval": 1000,
    "learner_log_interval": 1000,
    "t_max": 100000,
    "save_model": false,
    "save_model_interval": 50000,
    "checkpoint_path": "",
    "evaluate": false,
    "l2_reg_coef": 0,
    "gamma": 0.99,
    "repetitions": 5,
    "action_selector": "epsilon_greedy",
    "n_batches_to_sample": 1,
    "optimizer_epsilon": 0.0001,
    "use_cuda": true,
    "env_args": {
        "obs_entity_mode": false,
        "state_entity_mode": false,
        "env_name": "pistonball",
        "num_pistons": 15,
        "continuous": false,
        "episode_limit": 125,
        "time_penalty": -0.25,
        "seed": 0
    },
    "save_model_end": true,
    "buffer_transitions": false,
    "start_steps": 0,
    "env": "pettingzoo",
    "name": "maddpg_discrete",
    "seed": 0,
    "add_agent_id": false,
    "add_last_action": true,
    "critic_add_agent_id": false,
    "batch_size": 20,
    "buffer_size": 1000,
    "use_epsilon_greedy": true,
    "epsilon_start": 1.0,
    "epsilon_finish": 0.05,
    "epsilon_anneal_time": 70000,
    "evaluation_epsilon": 0,
    "lr": 0.001,
    "critic_lr": 0.001,
    "lr_decay_actor": false,
    "lr_decay_critic": false,
    "lr_decay_gamma": 0.9,
    "lr_decay_episodes": 20,
    "grad_norm_clip_actor": 0.5,
    "grad_norm_clip_critic": 0.5,
    "use_td_lambda": true,
    "td_lambda": 0.8,
    "learner": "maddpg_discrete_learner",
    "controller": "maddpg_discrete_controller",
    "critic_controller": "maddpg_discrete_critic_controller",
    "agent": "rnn",
    "critic": "centralized_mlp",
    "hidden_dim": 64,
    "hidden_dim_critic": 256,
    "target_update_mode": "soft",
    "target_update_tau": 0.005,
    "hard_update_interval": 200
}